Workbook

Sheet Models
A1: Pacific Classics — Bulletproof Classics & Youngtimers, Europe (1980–2011)
A2: Historic registration eligibility is calculated from the Rules sheet. Yellow columns are for your own deal tracking.
A3: ="Reference year: "&Rules!B11&" · Models: "&COUNT(A6:A200)&" · Fully FIVA-eligible now: "&COUNTIF(P6:P200,"Fully eligible") -> Reference year: 2026 · Models: 85 · Fully FIVA-eligible now: 30
A5: # | B5: Make | C5: Model | D5: Chassis | E5: Type · Segment | F5: Prod. from | G5: Prod. to | H5: Recommended engines | I5: Why it's bulletproof | J5: Watch out for | K5: Reliability (1-5) | L5: FIVA/EU 30y: first eligible year | M5: FIVA/EU 30y: all units eligible | N5: Italy ASI CRS 20y: first eligible year | O5: Eligible up to model year (30y) | P5: FIVA status today | Q5: Italy CRS status today | R5: Buy price DE/CZ (€) | S5: Resale price IT (€) | T5: Est. costs (€) | U5: Est. margin (€) | V5: Notes
A6: 1 | B6: Mercedes-Benz | C6: 190 | D6: W201 | E6: Sedan · Classic 1980s–90s | F6: 1982 | G6: 1993 | H6: 2.0D, 2.5D, 2.0/2.3 petrol | I6: Over-engineered; engines run 500,000+ km | J6: Rust: wheel arches, jacking points | K6: 5 | L6: =F6+Rules!$B$5 -> 2012 | M6: =G6+Rules!$B$5 -> 2023 | N6: =F6+Rules!$B$6 -> 2002 | O6: =MIN(G6,Rules!$B$11-Rules!$B$5) -> 1993 | P6: =IF(Rules!$B$11>=M6,"Fully eligible",IF(Rules!$B$11>=L6,"Partially eligible","Not yet")) -> Fully eligible | Q6: =IF(Rules!$B$11>=G6+Rules!$B$6,"Fully eligible",IF(Rules!$B$11>=N6,"Partially eligible","Not yet")) -> Fully eligible | U6: =IF(OR(R6="",S6=""),"",S6-R6-T6)
A7: 2 | B7: Mercedes-Benz | C7: E-Class | D7: W124 | E7: Sedan / Estate / Coupé · Classic 1980s–90s | F7: 1984 | G7: 1996 | H7: 200D/250D/300D (OM60x), 230E, 300E (M103) | I7: The benchmark; taxis with 1,000,000 km | J7: Biodegradable wiring 1993-95, rust | K7: 5 | L7: =F7+Rules!$B$5 -> 2014 | M7: =G7+Rules!$B$5 -> 2026 | N7: =F7+Rules!$B$6 -> 2004 | O7: =MIN(G7,Rules!$B$11-Rules!$B$5) -> 1996 | P7: =IF(Rules!$B$11>=M7,"Fully eligible",IF(Rules!$B$11>=L7,"Partially eligible","Not yet")) -> Fully eligible | Q7: =IF(Rules!$B$11>=G7+Rules!$B$6,"Fully eligible",IF(Rules!$B$11>=N7,"Partially eligible","Not yet")) -> Fully eligible | U7: =IF(OR(R7="",S7=""),"",S7-R7-T7)
A8: 3 | B8: Mercedes-Benz | C8: W123 (late units) | D8: W123 | E8: Sedan / Estate · Classic 1980s–90s | F8: 1976 | G8: 1985 | H8: 240D, 300D, 230E | I8: Indestructible, very simple mechanics | J8: Structural rust | K8: 5 | L8: =F8+Rules!$B$5 -> 2006 | M8: =G8+Rules!$B$5 -> 2015 | N8: =F8+Rules!$B$6 -> 1996 | O8: =MIN(G8,Rules!$B$11-Rules!$B$5) -> 1985 | P8: =IF(Rules!$B$11>=M8,"Fully eligible",IF(Rules!$B$11>=L8,"Partially eligible","Not yet")) -> Fully eligible | Q8: =IF(Rules!$B$11>=G8+Rules!$B$6,"Fully eligible",IF(Rules!$B$11>=N8,"Partially eligible","Not yet")) -> Fully eligible | U8: =IF(OR(R8="",S8=""),"",S8-R8-T8)
A9: 4 | B9: Mercedes-Benz | C9: S-Class | D9: W126 | E9: Sedan / Coupé · Classic 1980s–90s | F9: 1979 | G9: 1991 | H9: 300SE, 420SE, 300SD | I9: Flagship build quality, everlasting engines | J9: Parts cost, climate control | K9: 4 | L9: =F9+Rules!$B$5 -> 2009 | M9: =G9+Rules!$B$5 -> 2021 | N9: =F9+Rules!$B$6 -> 1999 | O9: =MIN(G9,Rules!$B$11-Rules!$B$5) -> 1991 | P9: =IF(Rules!$B$11>=M9,"Fully eligible",IF(Rules!$B$11>=L9,"Partially eligible","Not yet")) -> Fully eligible | Q9: =IF(Rules!$B$11>=G9+Rules!$B$6,"Fully eligible",IF(Rules!$B$11>=N9,"Partially eligible","Not yet")) -> Fully eligible | U9: =IF(OR(R9="",S9=""),"",S9-R9-T9)
A10: 5 | B10: Mercedes-Benz | C10: SL | D10: R107 | E10: Roadster · Classic 1980s–90s | F10: 1971 | G10: 1989 | H10: 300SL, 420SL, 500SL | I10: Very robust roadster, already an investment | J10: Rust under carpets | K10: 4 | L10: =F10+Rules!$B$5 -> 2001 | M10: =G10+Rules!$B$5 -> 2019 | N10: =F10+Rules!$B$6 -> 1991 | O10: =MIN(G10,Rules!$B$11-Rules!$B$5) -> 1989 | P10: =IF(Rules!$B$11>=M10,"Fully eligible",IF(Rules!$B$11>=L10,"Partially eligible","Not yet")) -> Fully eligible | Q10: =IF(Rules!$B$11>=G10+Rules!$B$6,"Fully eligible",IF(Rules!$B$11>=N10,"Partially eligible","Not yet")) -> Fully eligible | U10: =IF(OR(R10="",S10=""),"",S10-R10-T10)
A11: 6 | B11: Mercedes-Benz | C11: G-Class | D11: W460 / W463 | E11: 4x4 · Classic 1980s–90s | F11: 1979 | G11: 1996 | H11: 300GD, 250GD, 230GE | I11: Military-grade DNA | J11: Rust on frame and doors | K11: 5 | L11: =F11+Rules!$B$5 -> 2009 | M11: =G11+Rules!$B$5 -> 2026 | N11: =F11+Rules!$B$6 -> 1999 | O11: =MIN(G11,Rules!$B$11-Rules!$B$5) -> 1996 | P11: =IF(Rules!$B$11>=M11,"Fully eligible",IF(Rules!$B$11>=L11,"Partially eligible","Not yet")) -> Fully eligible | Q11: =IF(Rules!$B$11>=G11+Rules!$B$6,"Fully eligible",IF(Rules!$B$11>=N11,"Partially eligible","Not yet")) -> Fully eligible | U11: =IF(OR(R11="",S11=""),"",S11-R11-T11)
A12: 7 | B12: Mercedes-Benz | C12: SL | D12: R129 | E12: Roadster · Classic 1980s–90s | F12: 1989 | G12: 1996 | H12: 300SL, SL320, 500SL | I12: Built like a tank | J12: Soft-top hydraulics/electronics | K12: 4 | L12: =F12+Rules!$B$5 -> 2019 | M12: =G12+Rules!$B$5 -> 2026 | N12: =F12+Rules!$B$6 -> 2009 | O12: =MIN(G12,Rules!$B$11-Rules!$B$5) -> 1996 | P12: =IF(Rules!$B$11>=M12,"Fully eligible",IF(Rules!$B$11>=L12,"Partially eligible","Not yet")) -> Fully eligible | Q12: =IF(Rules!$B$11>=G12+Rules!$B$6,"Fully eligible",IF(Rules!$B$11>=N12,"Partially eligible","Not yet")) -> Fully eligible | U12: =IF(OR(R12="",S12=""),"",S12-R12-T12)
A13: 8 | B13: Volvo | C13: 240 / 245 | D13: 240 | E13: Sedan / Estate · Classic 1980s–90s | F13: 1974 | G13: 1993 | H13: B230F / B230FK | I13: The Swedish brick, 500,000+ km is normal | J13: Little; rust in low areas | K13: 5 | L13: =F13+Rules!$B$5 -> 2004 | M13: =G13+Rules!$B$5 -> 2023 | N13: =F13+Rules!$B$6 -> 1994 | O13: =MIN(G13,Rules!$B$11-Rules!$B$5) -> 1993 | P13: =IF(Rules!$B$11>=M13,"Fully eligible",IF(Rules!$B$11>=L13,"Partially eligible","Not yet")) -> Fully eligible | Q13: =IF(Rules!$B$11>=G13+Rules!$B$6,"Fully eligible",IF(Rules!$B$11>=N13,"Partially eligible","Not yet")) -> Fully eligible | U13: =IF(OR(R13="",S13=""),"",S13-R13-T13)
A14: 9 | B14: Volvo | C14: 740 / 760 | D14: 700 series | E14: Sedan / Estate · Classic 1980s–90s | F14: 1982 | G14: 1992 | H14: B230F, B230FT turbo | I14: Same mechanics as the 240 | J14: Worn automatic gearbox | K14: 5 | L14: =F14+Rules!$B$5 -> 2012 | M14: =G14+Rules!$B$5 -> 2022 | N14: =F14+Rules!$B$6 -> 2002 | O14: =MIN(G14,Rules!$B$11-Rules!$B$5) -> 1992 | P14: =IF(Rules!$B$11>=M14,"Fully eligible",IF(Rules!$B$11>=L14,"Partially eligible","Not yet")) -> Fully eligible | Q14: =IF(Rules!$B$11>=G14+Rules!$B$6,"Fully eligible",IF(Rules!$B$11>=N14,"Partially eligible","Not yet")) -> Fully eligible | U14: =IF(OR(R14="",S14=""),"",S14-R14-T14)
A15: 10 | B15: Volvo | C15: 940 / 960 | D15: 900 series | E15: Sedan / Estate · Classic 1980s–90s | F15: 1990 | G15: 1998 | H15: B230F/FT, 2.4 TD | I15: Evolution of the 740, easy parts | J15: 960 six-cylinder more delicate | K15: 4 | L15: =F15+Rules!$B$5 -> 2020 | M15: =G15+Rules!$B$5 -> 2028 | N15: =F15+Rules!$B$6 -> 2010 | O15: =MIN(G15,Rules!$B$11-Rules!$B$5) -> 1996 | P15: =IF(Rules!$B$11>=M15,"Fully eligible",IF(Rules!$B$11>=L15,"Partially eligible","Not yet")) -> Partially eligible | Q15: =IF(Rules!$B$11>=G15+Rules!$B$6,"Fully eligible",IF(Rules!$B$11>=N15,"Partially eligible","Not yet")) -> Fully eligible | U15: =IF(OR(R15="",S15=""),"",S15-R15-T15)
A16: 11 | B16: Volvo | C16: 850 | D16: 850 | E16: Sedan / Estate · Classic 1980s–90s | F16: 1991 | G16: 1996 | H16: 2.0/2.5 5-cyl naturally aspirated | I16: Very robust 5-cylinder | J16: AW50 automatic gearbox | K16: 4 | L16: =F16+Rules!$B$5 -> 2021 | M16: =G16+Rules!$B$5 -> 2026 | N16: =F16+Rules!$B$6 -> 2011 | O16: =MIN(G16,Rules!$B$11-Rules!$B$5) -> 1996 | P16: =IF(Rules!$B$11>=M16,"Fully eligible",IF(Rules!$B$11>=L16,"Partially eligible","Not yet")) -> Fully eligible | Q16: =IF(Rules!$B$11>=G16+Rules!$B$6,"Fully eligible",IF(Rules!$B$11>=N16,"Partially eligible","Not yet")) -> Fully eligible | U16: =IF(OR(R16="",S16=""),"",S16-R16-T16)
A17: 12 | B17: Toyota | C17: Land Cruiser | D17: J60 / J70 / J80 | E17: 4x4 · Classic 1980s–90s | F17: 1980 | G17: 1997 | H17: 1HZ, 1HD-T, 12H-T, 3F | I17: Possibly the most reliable vehicle ever made | J17: High prices, frame rust | K17: 5 | L17: =F17+Rules!$B$5 -> 2010 | M17: =G17+Rules!$B$5 -> 2027 | N17: =F17+Rules!$B$6 -> 2000 | O17: =MIN(G17,Rules!$B$11-Rules!$B$5) -> 1996 | P17: =IF(Rules!$B$11>=M17,"Fully eligible",IF(Rules!$B$11>=L17,"Partially eligible","Not yet")) -> Partially eligible | Q17: =IF(Rules!$B$11>=G17+Rules!$B$6,"Fully eligible",IF(Rules!$B$11>=N17,"Partially eligible","Not yet")) -> Fully eligible | U17: =IF(OR(R17="",S17=""),"",S17-R17-T17)
... A90: 85 | B90: Fiat | C90: Doblò I | D90: 119/223 | E90: Van / MPV · Youngtimer 1997–2011 | F90: 2001 | G90: 2011 | H90: 1.9 JTD / Multijet, 1.4 petrol | I90: 1.9 JTD: robust Fiat diesel, cheap parts in Italy | J90: Rust, front suspension | K90: 4 | L90: =F90+Rules!$B$5 -> 2031 | M90: =G90+Rules!$B$5 -> 2041 | N90: =F90+Rules!$B$6 -> 2021 | O90: =MIN(G90,Rules!$B$11-Rules!$B$5) -> 1996 | P90: =IF(Rules!$B$11>=M90,"Fully eligible",IF(Rules!$B$11>=L90,"Partially eligible","Not yet")) -> Not yet | Q90: =IF(Rules!$B$11>=G90+Rules!$B$6,"Fully eligible",IF(Rules!$B$11>=N90,"Partially eligible","Not yet")) -> Partially eligible | U90: =IF(OR(R90="",S90=""),"",S90-R90-T90)
B92: Legend
B93: Yellow cells | C93: Your inputs: buy price, resale price, costs, notes. Margin = Resale − Buy − Costs.
B94: Example | C94: e.g. Buy 4,500 · Resale 7,500 · Costs 1,200 → Margin € 1,800
B95: Green / Amber / Red | C95: Fully eligible / only older production years eligible / not yet eligible
B96: Thresholds | C96: Change ages or reference year in the Rules sheet

Sheet Rules
A1: Historic Registration Rules
A2: Age thresholds used by the Models sheet. Edit the yellow cells to change every calculation.
A4: Scheme | B4: Min. age (years) | C4: Notes
A5: FIVA / EU standard (30 y) | B5: 30 | C5: FIVA definition of historic vehicle: 30+ years, preserved in historically correct condition, not used as daily transport.
A6: Italy - ASI CRS (20 y) | B6: 20 | C6: Certificato di Rilevanza Storica from ASI: available from 20 years for models of historic/collector interest. Veicolo d'epoca status (ASI/FMI) and full road-tax exemption rules vary by region.
A7: France - Carte grise collection | B7: 30 | C7: Carte grise 'véhicule de collection': 30 years, FFVE certificate required.
A8: Czech Rep. - Historic plate (H) | B8: 30 | C8: Historické vozidlo: 30 years + technical inspection by a historic vehicle commission (STK).
A9: Germany - H-Kennzeichen | B9: 30 | C9: H plate: 30 years + §23 StVZO appraisal (largely original, good condition).
A11: Reference year | B11: =YEAR(TODAY()) -> 2026 | C11: Updates automatically. Replace with a fixed year (blue input) to plan ahead.
A13: Rules summarised from FIVA, ASI, FFVE, Czech and German regulations; always verify with the local registry/club before buying.
